TorchMiner/__init__.py
TorchMiner/Logger.py
TorchMiner/miner.py
TorchMiner/plugins/__init__.py
TorchMiner/plugins/Logger/__init__.py
TorchMiner/plugins/Logger/Jupyter.py
TorchMiner/plugins/Metrics/__init__.py
TorchMiner/plugins/Metrics/Classification.py
TorchMiner/plugins/Metrics/Regression.py
TorchMiner/plugins/noise_detector.py
TorchMiner/plugins/Plugin.py
TorchMiner/plugins/Recorder/__init__.py
TorchMiner/plugins/Recorder/BasicSheet.py
TorchMiner/plugins/Recorder/GoogleSheet.py
TorchMiner/plugins/Recorder/TensorBoard.py
TorchMiner/plugins/Runtime.py
TorchMiner/README.md
TorchMiner/utils.py
torchminer-0.4.14.dist-info/WHEEL
torchminer-0.4.14.dist-info/METADATA
torchminer-0.4.14.dist-info/RECORD
